{"id": 50, "name": "AbdulBaset AbdulSamad [Mujawwad]", "arabicName": "\u0639\u0628\u062f \u0627\u0644\u0628\u0627\u0633\u0637 \u0639\u0628\u062f \u0627\u0644\u0635\u0645\u062f - \u0645\u062c\u0648\u062f", "surahs": [{"file_name": "001.mp3", "size": "1595520", "bitrate": "128721", "duration": "99.160813", "title": "Surat Al-Fatiha", "link": "https://download.quranicaudio.com/quran/abdulbaset_mujawwad/001.mp3"}, {"file_name": "002.mp3", "size": "253595776", "bitrate": "128005", "duration": "15849.116689", "title": "Surat Al-Baqara", "link": "https://download.quranicaudio.com/quran/abdulbaset_mujawwad/002.mp3"}, {"file_name": "003.mp3", "size": "149495936", "bitrate": "128009", "duration": "9342.829938", "title": "Surat Aal-E-Imran", "link": "https://download.quranicaudio.com/quran/abdulbaset_mujawwad/003.mp3"}, {"file_name": "004.mp3", "size": "161222784", "bitrate": "128007", "duration": "10075.854500", "title": "Surat An-Nisa", "link": "https://download.quranicaudio.com/quran/abdulbaset_mujawwad/004.mp3"}, {"file_name": "005.mp3", "size": "126113920", "bitrate": "128009", "duration": "7881.534689", "title": "Surat Al-Maeda", "link": "https://download.quranicaudio.com/quran/abdulbaset_mujawwad/005.mp3"}, {"file_name": "006.mp3", "size": "134551680", "bitrate": "128008", "duration": "8408.920813", "title": "Surat Al-Anaam", "link": "https://download.quranicaudio.com/quran/abdulbaset_mujawwad/006.mp3"}, {"file_name": "007.mp3", "size": "149360768", "bitrate": "128007", "duration": "9334.491378", "title": "Surat Al-Araf", "link": "https://download.quranicaudio.com/quran/abdulbaset_mujawwad/007.mp3"}, {"file_name": "008.mp3", "size": "54759552", "bitrate": "128024", "duration": "3421.805689", "title": "Surat Al-Anfal", "link": "https://download.quranicaudio.com/quran/abdulbaset_mujawwad/008.mp3"}, {"file_name": "009.mp3", "size": "108818560", "bitrate": "128011", "duration": "6800.535500", "title": "Surat At-Tawba", "link": "https://download.quranicaudio.com/quran/abdulbaset_mujawwad/009.mp3"}, {"file_name": "010.mp3", "size": "77355136", "bitrate": "128016", "duration": "4834.089756", "title": "Surat Yunus", "link": "https://download.quranicaudio.com/quran/abdulbaset_mujawwad/010.mp3"}, {"file_name": "011.mp3", "size": "85090432", "bitrate": "128015", "duration": "5317.511813", "title": "Surat Hud", "link": "https://download.quranicaudio.com/quran/abdulbaset_mujawwad/011.mp3"}, {"file_name": "012.mp3", "size": "78697831", "bitrate": "128015", "duration": "4918.003067", "title": "Surat Yusuf", "link": "https://download.quranicaudio.com/quran/abdulbaset_mujawwad/012.mp3"}, {"file_name": "013.mp3", "size": "37406848", "bitrate": "128031", "duration": "2337.358313", "title": "Surat Ar-Rad", "link": "https://download.quranicaudio.com/quran/abdulbaset_mujawwad/013.mp3"}, {"file_name": "014.mp3", "size": "38279296", "bitrate": "128031", "duration": "2391.875878", "title": "Surat Ibrahim", "link": "https://download.quranicaudio.com/quran/abdulbaset_mujawwad/014.mp3"}, {"file_name": "015.mp3", "size": "33988736", "bitrate": "128040", "duration": "2123.624438", "title": "Surat Al-Hijr", "link": "https://download.quranicaudio.com/quran/abdulbaset_mujawwad/015.mp3"}, {"file_name": "016.mp3", "size": "83792000", "bitrate": "128015", "duration": "5236.375500", "title": "Surat An-Nahl", "link": "https://download.quranicaudio.com/quran/abdulbaset_mujawwad/016.mp3"}, {"file_name": "017.mp3", "size": "66109568", "bitrate": "128020", "duration": "4131.186813", "title": "Surat Al-Isra", "link": "https://download.quranicaudio.com/quran/abdulbaset_mujawwad/017.mp3"}, {"file_name": "018.mp3", "size": "67160192", "bitrate": "128016", "duration": "4196.963256", "title": "Surat Al-Kahf", "link": "https://download.quranicaudio.com/quran/abdulbaset_mujawwad/018.mp3"}, {"file_name": "019.mp3", "size": "41142400", "bitrate": "128029", "duration": "2570.814689", "title": "Surat Maryam", "link": "https://download.quranicaudio.com/quran/abdulbaset_mujawwad/019.mp3"}, {"file_name": "020.mp3", "size": "57305216", "bitrate": "128019", "duration": "3581.022000", "title": "Surat Ta-Ha", "link": "https://download.quranicaudio.com/quran/abdulbaset_mujawwad/020.mp3"}, {"file_name": "021.mp3", "size": "54560896", "bitrate": "128022", "duration": "3409.449756", "title": "Surat Al-Anbiya", "link": "https://download.quranicaudio.com/quran/abdulbaset_mujawwad/021.mp3"}, {"file_name": "022.mp3", "size": "55949440", "bitrate": "128022", "duration": "3496.228567", "title": "Surat Al-Hajj", "link": "https://download.quranicaudio.com/quran/abdulbaset_mujawwad/022.mp3"}, {"file_name": "023.mp3", "size": "49285248", "bitrate": "128026", "duration": "3079.679878", "title": "Surat Al-Mumenoon", "link": "https://download.quranicaudio.com/quran/abdulbaset_mujawwad/023.mp3"}, {"file_name": "024.mp3", "size": "62044288", "bitrate": "128021", "duration": "3877.119878", "title": "Surat An-Noor", "link": "https://download.quranicaudio.com/quran/abdulbaset_mujawwad/024.mp3"}, {"file_name": "025.mp3", "size": "39727232", "bitrate": "128030", "duration": "2482.364067", "title": "Surat Al-Furqan", "link": "https://download.quranicaudio.com/quran/abdulbaset_mujawwad/025.mp3"}, {"file_name": "026.mp3", "size": "68726912", "bitrate": "128019", "duration": "4294.765689", "title": "Surat Ash-Shu'ara", "link": "https://download.quranicaudio.com/quran/abdulbaset_mujawwad/026.mp3"}, {"file_name": "027.mp3", "size": "51099776", "bitrate": "128023", "duration": "3193.155878", "title": "Surat An-Naml", "link": "https://download.quranicaudio.com/quran/abdulbaset_mujawwad/027.mp3"}, {"file_name": "028.mp3", "size": "62394496", "bitrate": "128021", "duration": "3899.010567", "title": "Surat Al-Qasas", "link": "https://download.quranicaudio.com/quran/abdulbaset_mujawwad/028.mp3"}, {"file_name": "029.mp3", "size": "46100608", "bitrate": "128025", "duration": "2880.705256", "title": "Surat Al-Ankaboot", "link": "https://download.quranicaudio.com/quran/abdulbaset_mujawwad/029.mp3"}, {"file_name": "030.mp3", "size": "58595456", "bitrate": "128020", "duration": "3661.635878", "title": "Surat Ar-Room", "link": "https://download.quranicaudio.com/quran/abdulbaset_mujawwad/030.mp3"}, {"file_name": "031.mp3", "size": "22425728", "bitrate": "128056", "duration": "1400.989000", "title": "Surat Luqman", "link": "https://download.quranicaudio.com/quran/abdulbaset_mujawwad/031.mp3"}, {"file_name": "032.mp3", "size": "15917184", "bitrate": "128084", "duration": "994.168125", "title": "Surat As-Sajda", "link": "https://download.quranicaudio.com/quran/abdulbaset_mujawwad/032.mp3"}, {"file_name": "033.mp3", "size": "57456768", "bitrate": "128024", "duration": "3590.373878", "title": "Surat Al-Ahzab", "link": "https://download.quranicaudio.com/quran/abdulbaset_mujawwad/033.mp3"}, {"file_name": "034.mp3", "size": "37224576", "bitrate": "128031", "duration": "2325.968938", "title": "Surat Saba", "link": "https://download.quranicaudio.com/quran/abdulbaset_mujawwad/034.mp3"}, {"file_name": "035.mp3", "size": "34447488", "bitrate": "128036", "duration": "2152.359125", "title": "Surat Fatir", "link": "https://download.quranicaudio.com/quran/abdulbaset_mujawwad/035.mp3"}, {"file_name": "036.mp3", "size": "33753216", "bitrate": "128036", "duration": "2108.969756", "title": "Surat Ya-Seen", "link": "https://download.quranicaudio.com/quran/abdulbaset_mujawwad/036.mp3"}, {"file_name": "037.mp3", "size": "50184320", "bitrate": "128024", "duration": "3135.921625", "title": "Surat As-Saaffat", "link": "https://download.quranicaudio.com/quran/abdulbaset_mujawwad/037.mp3"}, {"file_name": "038.mp3", "size": "35532928", "bitrate": "128035", "duration": "2220.199125", "title": "Surat Sad", "link": "https://download.quranicaudio.com/quran/abdulbaset_mujawwad/038.mp3"}, {"file_name": "039.mp3", "size": "53094528", "bitrate": "128025", "duration": "3317.759878", "title": "Surat Az-Zumar", "link": "https://download.quranicaudio.com/quran/abdulbaset_mujawwad/039.mp3"}, {"file_name": "040.mp3", "size": "54601856", "bitrate": "128022", "duration": "3412.009756", "title": "Surat Al-Ghafir", "link": "https://download.quranicaudio.com/quran/abdulbaset_mujawwad/040.mp3"}, {"file_name": "041.mp3", "size": "36454528", "bitrate": "128034", "duration": "2277.799125", "title": "Surat Fussilat", "link": "https://download.quranicaudio.com/quran/abdulbaset_mujawwad/041.mp3"}, {"file_name": "042.mp3", "size": "37761152", "bitrate": "128036", "duration": "2359.405689", "title": "Surat Ash-Shura", "link": "https://download.quranicaudio.com/quran/abdulbaset_mujawwad/042.mp3"}, {"file_name": "043.mp3", "size": "39747712", "bitrate": "128031", "duration": "2483.617938", "title": "Surat Az-Zukhruf", "link": "https://download.quranicaudio.com/quran/abdulbaset_mujawwad/043.mp3"}, {"file_name": "044.mp3", "size": "18047104", "bitrate": "128067", "duration": "1127.348313", "title": "Surat Ad-Dukhan", "link": "https://download.quranicaudio.com/quran/abdulbaset_mujawwad/044.mp3"}, {"file_name": "045.mp3", "size": "21913728", "bitrate": "128056", "duration": "1369.007125", "title": "Surat Al-Jathiya", "link": "https://download.quranicaudio.com/quran/abdulbaset_mujawwad/045.mp3"}, {"file_name": "046.mp3", "size": "29646976", "bitrate": "128043", "duration": "1852.306625", "title": "Surat Al-Ahqaf", "link": "https://download.quranicaudio.com/quran/abdulbaset_mujawwad/046.mp3"}, {"file_name": "047.mp3", "size": "24672384", "bitrate": "128046", "duration": "1541.459567", "title": "Surat Muhammad", "link": "https://download.quranicaudio.com/quran/abdulbaset_mujawwad/047.mp3"}, {"file_name": "048.mp3", "size": "25047168", "bitrate": "128047", "duration": "1564.865256", "title": "Surat Al-Fath", "link": "https://download.quranicaudio.com/quran/abdulbaset_mujawwad/048.mp3"}, {"file_name": "049.mp3", "size": "17447040", "bitrate": "128065", "duration": "1089.880813", "title": "Surat Al-Hujraat", "link": "https://download.quranicaudio.com/quran/abdulbaset_mujawwad/049.mp3"}, {"file_name": "050.mp3", "size": "17377408", "bitrate": "128067", "duration": "1085.518313", "title": "Surat Qaf", "link": "https://download.quranicaudio.com/quran/abdulbaset_mujawwad/050.mp3"}, {"file_name": "051.mp3", "size": "17526912", "bitrate": "128077", "duration": "1094.765689", "title": "Surat Adh-Dhariyat", "link": "https://download.quranicaudio.com/quran/abdulbaset_mujawwad/051.mp3"}, {"file_name": "052.mp3", "size": "15310976", "bitrate": "128075", "duration": "956.368938", "title": "Surat At-Tur", "link": "https://download.quranicaudio.com/quran/abdulbaset_mujawwad/052.mp3"}, {"file_name": "053.mp3", "size": "16445568", "bitrate": "128079", "duration": "1027.213000", "title": "Surat An-Najm", "link": "https://download.quranicaudio.com/quran/abdulbaset_mujawwad/053.mp3"}, {"file_name": "054.mp3", "size": "16410752", "bitrate": "128071", "duration": "1025.097125", "title": "Surat Al-Qamar", "link": "https://download.quranicaudio.com/quran/abdulbaset_mujawwad/054.mp3"}, {"file_name": "055.mp3", "size": "20093056", "bitrate": "128061", "duration": "1255.209756", "title": "Surat Ar-Rahman", "link": "https://download.quranicaudio.com/quran/abdulbaset_mujawwad/055.mp3"}, {"file_name": "056.mp3", "size": "19794048", "bitrate": "128067", "duration": "1236.479878", "title": "Surat Al-Waqia", "link": "https://download.quranicaudio.com/quran/abdulbaset_mujawwad/056.mp3"}, {"file_name": "057.mp3", "size": "26751104", "bitrate": "128044", "duration": "1671.366500", "title": "Surat Al-Hadid", "link": "https://download.quranicaudio.com/quran/abdulbaset_mujawwad/057.mp3"}, {"file_name": "058.mp3", "size": "22614144", "bitrate": "128059", "duration": "1412.728125", "title": "Surat Al-Mujadila", "link": "https://download.quranicaudio.com/quran/abdulbaset_mujawwad/058.mp3"}, {"file_name": "059.mp3", "size": "22159488", "bitrate": "128053", "duration": "1384.385256", "title": "Surat Al-Hashr", "link": "https://download.quranicaudio.com/quran/abdulbaset_mujawwad/059.mp3"}, {"file_name": "060.mp3", "size": "18026624", "bitrate": "128074", "duration": "1126.008125", "title": "Surat Al-Mumtahina", "link": "https://download.quranicaudio.com/quran/abdulbaset_mujawwad/060.mp3"}, {"file_name": "061.mp3", "size": "10160256", "bitrate": "128127", "duration": "634.383625", "title": "Surat As-Saff", "link": "https://download.quranicaudio.com/quran/abdulbaset_mujawwad/061.mp3"}, {"file_name": "062.mp3", "size": "7862400", "bitrate": "128159", "duration": "490.788567", "title": "Surat Al-Jumua", "link": "https://download.quranicaudio.com/quran/abdulbaset_mujawwad/062.mp3"}, {"file_name": "063.mp3", "size": "8444032", "bitrate": "128145", "duration": "527.151000", "title": "Surat Al-Munafiqoon", "link": "https://download.quranicaudio.com/quran/abdulbaset_mujawwad/063.mp3"}, {"file_name": "064.mp3", "size": "11151488", "bitrate": "128104", "duration": "696.398313", "title": "Surat At-Taghabun", "link": "https://download.quranicaudio.com/quran/abdulbaset_mujawwad/064.mp3"}, {"file_name": "065.mp3", "size": "13101184", "bitrate": "128092", "duration": "818.233438", "title": "Surat At-Talaq", "link": "https://download.quranicaudio.com/quran/abdulbaset_mujawwad/065.mp3"}, {"file_name": "066.mp3", "size": "12046464", "bitrate": "128111", "duration": "752.248125", "title": "Surat At-Tahrim", "link": "https://download.quranicaudio.com/quran/abdulbaset_mujawwad/066.mp3"}, {"file_name": "067.mp3", "size": "13658240", "bitrate": "128091", "duration": "853.028567", "title": "Surat Al-Mulk", "link": "https://download.quranicaudio.com/quran/abdulbaset_mujawwad/067.mp3"}, {"file_name": "068.mp3", "size": "14704768", "bitrate": "128088", "duration": "918.413000", "title": "Surat Al-Qalam", "link": "https://download.quranicaudio.com/quran/abdulbaset_mujawwad/068.mp3"}, {"file_name": "069.mp3", "size": "12406912", "bitrate": "128101", "duration": "774.817938", "title": "Surat Al-Haaqqa", "link": "https://download.quranicaudio.com/quran/abdulbaset_mujawwad/069.mp3"}, {"file_name": "070.mp3", "size": "10260608", "bitrate": "128111", "duration": "640.731378", "title": "Surat Al-Maarij", "link": "https://download.quranicaudio.com/quran/abdulbaset_mujawwad/070.mp3"}, {"file_name": "071.mp3", "size": "9085056", "bitrate": "128127", "duration": "567.248938", "title": "Surat Nooh", "link": "https://download.quranicaudio.com/quran/abdulbaset_mujawwad/071.mp3"}, {"file_name": "072.mp3", "size": "11262080", "bitrate": "128101", "duration": "703.320813", "title": "Surat Al-Jinn", "link": "https://download.quranicaudio.com/quran/abdulbaset_mujawwad/072.mp3"}, {"file_name": "073.mp3", "size": "8476800", "bitrate": "128147", "duration": "529.188567", "title": "Surat Al-Muzzammil", "link": "https://download.quranicaudio.com/quran/abdulbaset_mujawwad/073.mp3"}, {"file_name": "074.mp3", "size": "11184256", "bitrate": "128111", "duration": "698.409756", "title": "Surat Al-Muddaththir", "link": "https://download.quranicaudio.com/quran/abdulbaset_mujawwad/074.mp3"}, {"file_name": "075.mp3", "size": "7102592", "bitrate": "128162", "duration": "443.350189", "title": "Surat Al-Qiyama", "link": "https://download.quranicaudio.com/quran/abdulbaset_mujawwad/075.mp3"}, {"file_name": "076.mp3", "size": "11563136", "bitrate": "128119", "duration": "722.024438", "title": "Surat Al-Insan", "link": "https://download.quranicaudio.com/quran/abdulbaset_mujawwad/076.mp3"}, {"file_name": "077.mp3", "size": "9386112", "bitrate": "128125", "duration": "586.057125", "title": "Surat Al-Mursalat", "link": "https://download.quranicaudio.com/quran/abdulbaset_mujawwad/077.mp3"}, {"file_name": "078.mp3", "size": "8349824", "bitrate": "128157", "duration": "521.221189", "title": "Surat An-Naba", "link": "https://download.quranicaudio.com/quran/abdulbaset_mujawwad/078.mp3"}, {"file_name": "079.mp3", "size": "7772288", "bitrate": "128150", "duration": "485.198313", "title": "Surat An-Naziat", "link": "https://download.quranicaudio.com/quran/abdulbaset_mujawwad/079.mp3"}, {"file_name": "080.mp3", "size": "6183040", "bitrate": "128220", "duration": "385.776313", "title": "Surat Abasa", "link": "https://download.quranicaudio.com/quran/abdulbaset_mujawwad/080.mp3"}, {"file_name": "081.mp3", "size": "4927616", "bitrate": "128257", "duration": "307.356689", "title": "Surat At-Takwir", "link": "https://download.quranicaudio.com/quran/abdulbaset_mujawwad/081.mp3"}, {"file_name": "082.mp3", "size": "3969152", "bitrate": "128304", "duration": "247.484067", "title": "Surat Al-Infitar", "link": "https://download.quranicaudio.com/quran/abdulbaset_mujawwad/082.mp3"}, {"file_name": "083.mp3", "size": "8499328", "bitrate": "128140", "duration": "530.625256", "title": "Surat Al-Mutaffifin", "link": "https://download.quranicaudio.com/quran/abdulbaset_mujawwad/083.mp3"}, {"file_name": "084.mp3", "size": "4964480", "bitrate": "128233", "duration": "309.715813", "title": "Surat Al-Inshiqaq", "link": "https://download.quranicaudio.com/quran/abdulbaset_mujawwad/084.mp3"}, {"file_name": "085.mp3", "size": "5382272", "bitrate": "128254", "duration": "335.725689", "title": "Surat Al-Burooj", "link": "https://download.quranicaudio.com/quran/abdulbaset_mujawwad/085.mp3"}, {"file_name": "086.mp3", "size": "3037312", "bitrate": "128383", "duration": "189.265189", "title": "Surat At-Tariq", "link": "https://download.quranicaudio.com/quran/abdulbaset_mujawwad/086.mp3"}, {"file_name": "087.mp3", "size": "4229248", "bitrate": "128276", "duration": "263.758313", "title": "Surat Al-Ala", "link": "https://download.quranicaudio.com/quran/abdulbaset_mujawwad/087.mp3"}, {"file_name": "088.mp3", "size": "5339264", "bitrate": "128236", "duration": "333.087313", "title": "Surat Al-Ghashiya", "link": "https://download.quranicaudio.com/quran/abdulbaset_mujawwad/088.mp3"}, {"file_name": "089.mp3", "size": "7180416", "bitrate": "128176", "duration": "448.156689", "title": "Surat Al-Fajr", "link": "https://download.quranicaudio.com/quran/abdulbaset_mujawwad/089.mp3"}, {"file_name": "090.mp3", "size": "4071552", "bitrate": "128322", "duration": "253.831813", "title": "Surat Al-Balad", "link": "https://download.quranicaudio.com/quran/abdulbaset_mujawwad/090.mp3"}, {"file_name": "091.mp3", "size": "3471488", "bitrate": "128367", "duration": "216.346067", "title": "Surat Ash-Shams", "link": "https://download.quranicaudio.com/quran/abdulbaset_mujawwad/091.mp3"}, {"file_name": "092.mp3", "size": "4143232", "bitrate": "128297", "duration": "258.351000", "title": "Surat Al-Lail", "link": "https://download.quranicaudio.com/quran/abdulbaset_mujawwad/092.mp3"}, {"file_name": "093.mp3", "size": "2269312", "bitrate": "128604", "duration": "141.165689", "title": "Surat Ad-Dhuha", "link": "https://download.quranicaudio.com/quran/abdulbaset_mujawwad/093.mp3"}, {"file_name": "094.mp3", "size": "1587328", "bitrate": "128841", "duration": "98.559878", "title": "Surat Al-Inshirah", "link": "https://download.quranicaudio.com/quran/abdulbaset_mujawwad/094.mp3"}, {"file_name": "095.mp3", "size": "1783936", "bitrate": "128760", "duration": "110.837500", "title": "Surat At-Tin", "link": "https://download.quranicaudio.com/quran/abdulbaset_mujawwad/095.mp3"}, {"file_name": "096.mp3", "size": "3293312", "bitrate": "128415", "duration": "205.165689", "title": "Surat Al-Alaq", "link": "https://download.quranicaudio.com/quran/abdulbaset_mujawwad/096.mp3"}, {"file_name": "097.mp3", "size": "1351808", "bitrate": "129009", "duration": "83.826813", "title": "Surat Al-Qadr", "link": "https://download.quranicaudio.com/quran/abdulbaset_mujawwad/097.mp3"}, {"file_name": "098.mp3", "size": "4028544", "bitrate": "128314", "duration": "251.167313", "title": "Surat Al-Bayyina", "link": "https://download.quranicaudio.com/quran/abdulbaset_mujawwad/098.mp3"}, {"file_name": "099.mp3", "size": "1970304", "bitrate": "128685", "duration": "122.488125", "title": "Surat Az-Zalzala", "link": "https://download.quranicaudio.com/quran/abdulbaset_mujawwad/099.mp3"}, {"file_name": "100.mp3", "size": "2240640", "bitrate": "128573", "duration": "139.415500", "title": "Surat Al-Adiyat", "link": "https://download.quranicaudio.com/quran/abdulbaset_mujawwad/100.mp3"}, {"file_name": "101.mp3", "size": "1958016", "bitrate": "128651", "duration": "121.756689", "title": "Surat Al-Qaria", "link": "https://download.quranicaudio.com/quran/abdulbaset_mujawwad/101.mp3"}, {"file_name": "102.mp3", "size": "1732736", "bitrate": "128704", "duration": "107.702813", "title": "Surat At-Takathur", "link": "https://download.quranicaudio.com/quran/abdulbaset_mujawwad/102.mp3"}, {"file_name": "103.mp3", "size": "798848", "bitrate": "129648", "duration": "49.293000", "title": "Surat Al-Asr", "link": "https://download.quranicaudio.com/quran/abdulbaset_mujawwad/103.mp3"}, {"file_name": "104.mp3", "size": "1642624", "bitrate": "128790", "duration": "102.034256", "title": "Surat Al-Humaza", "link": "https://download.quranicaudio.com/quran/abdulbaset_mujawwad/104.mp3"}, {"file_name": "105.mp3", "size": "1394816", "bitrate": "128896", "duration": "86.569756", "title": "Surat Al-Fil", "link": "https://download.quranicaudio.com/quran/abdulbaset_mujawwad/105.mp3"}, {"file_name": "106.mp3", "size": "1136768", "bitrate": "129130", "duration": "70.426067", "title": "Surat Quraish", "link": "https://download.quranicaudio.com/quran/abdulbaset_mujawwad/106.mp3"}, {"file_name": "107.mp3", "size": "1665152", "bitrate": "128808", "duration": "103.418756", "title": "Surat Al-Maun", "link": "https://download.quranicaudio.com/quran/abdulbaset_mujawwad/107.mp3"}, {"file_name": "108.mp3", "size": "714880", "bitrate": "129930", "duration": "44.016313", "title": "Surat Al-Kauther", "link": "https://download.quranicaudio.com/quran/abdulbaset_mujawwad/108.mp3"}, {"file_name": "109.mp3", "size": "1462400", "bitrate": "128917", "duration": "90.749378", "title": "Surat Al-Kafiroon", "link": "https://download.quranicaudio.com/quran/abdulbaset_mujawwad/109.mp3"}, {"file_name": "110.mp3", "size": "999552", "bitrate": "129325", "duration": "61.831813", "title": "Surat An-Nasr", "link": "https://download.quranicaudio.com/quran/abdulbaset_mujawwad/110.mp3"}, {"file_name": "111.mp3", "size": "1149056", "bitrate": "129042", "duration": "71.235878", "title": "Surat Al-Masadd", "link": "https://download.quranicaudio.com/quran/abdulbaset_mujawwad/111.mp3"}, {"file_name": "112.mp3", "size": "667776", "bitrate": "130010", "duration": "41.090567", "title": "Surat Al-Ikhlas", "link": "https://download.quranicaudio.com/quran/abdulbaset_mujawwad/112.mp3"}, {"file_name": "113.mp3", "size": "1022080", "bitrate": "129183", "duration": "63.294689", "title": "Surat Al-Falaq", "link": "https://download.quranicaudio.com/quran/abdulbaset_mujawwad/113.mp3"}, {"file_name": "114.mp3", "size": "1345664", "bitrate": "128945", "duration": "83.487313", "title": "Surat An-Nas", "link": "https://download.quranicaudio.com/quran/abdulbaset_mujawwad/114.mp3"}]}